fastarg/__init__.py
fastarg/main.py
fastarg-0.1.2.dist-info/LICENSE
fastarg-0.1.2.dist-info/METADATA
fastarg-0.1.2.dist-info/WHEEL
fastarg-0.1.2.dist-info/top_level.txt
fastarg-0.1.2.dist-info/RECORD
